CHANGELOG.txt
LICENCE.txt
MANIFEST.in
README.txt
setup.py
best_snomed/__init__.py
best_snomed.egg-info/PKG-INFO
best_snomed.egg-info/SOURCES.txt
best_snomed.egg-info/dependency_links.txt
best_snomed.egg-info/requires.txt
best_snomed.egg-info/top_level.txt